requestlog/__init__.py
requestlog/decorators.py
requestlog/globals.py
requestlog/log_queue.py
requestlog/log_record.py
requestlog/sinks.py
requestlog-0.1.1.dist-info/LICENSE
requestlog-0.1.1.dist-info/METADATA
requestlog-0.1.1.dist-info/WHEEL
requestlog-0.1.1.dist-info/RECORD
