Metadata-Version: 2.1
Name: requestlog
Version: 0.1.1
Summary: Structured request logging in Python
License: MIT
Author: Rico Hermans
Author-email: rix0rrr@gmail.com
Requires-Python: >=3.9,<4.0
Classifier: License :: OSI Approved :: MIT License
Classifier: Programming Language :: Python :: 3
Classifier: Programming Language :: Python :: 3.9
Classifier: Programming Language :: Python :: 3.10
Classifier: Programming Language :: Python :: 3.11
Classifier: Programming Language :: Python :: 3.12
